streamlit_avater/__init__.py
streamlit_avater/frontend/build/asset-manifest.json
streamlit_avater/frontend/build/bootstrap.min.css
streamlit_avater/frontend/build/index.html
streamlit_avater/frontend/build/static/js/main.058df7e9.js
streamlit_avater/frontend/build/static/js/main.058df7e9.js.LICENSE.txt
streamlit_avater/frontend/build/static/js/main.058df7e9.js.map
streamlit_avater-0.1.0.dist-info/LICENSE
streamlit_avater-0.1.0.dist-info/METADATA
streamlit_avater-0.1.0.dist-info/WHEEL
streamlit_avater-0.1.0.dist-info/top_level.txt
streamlit_avater-0.1.0.dist-info/RECORD
